{
  "active_feature_file": null,
  "phase": "DONE",
  "HUMAN_APPROVED": false,
  "state_tag": "IDLE",
  "last_agent": "orchestrator",
  "recent_log": [
    "2026-06-21: dashboard-sales-widgets DONE. KB-010 added. All 9 original backlog items now DONE: pnl-asset-liability-fix, vendor-payment-receipt-voucher, invoice-quick-close, dispatch-delivery-agent-filter, invoice-preview, expense-direct-indirect-categories, coa-hide-balance-values, production-quality-scanning, dashboard-sales-widgets.",
    "2026-06-21: Nothing committed to git yet this session -- all 9 features' changes sit together uncommitted in the working tree. Two new Prisma migrations (vendor-payment-receipt-voucher, expense-direct-indirect-categories) not yet applied to any DB. Backlog empty, awaiting new work."
  ]
}
